picamip/__init__.py
picamip/picamera.py
picamip/server.py
picamip/storage.py
picamip/static/GitHub-Mark-32px.png
picamip/static/favicon.ico
picamip/static/main.js
picamip/static/paginator.js
picamip/static/stylesheet.css
picamip/static/bootstrap/bootstrap-icons.svg
picamip/static/bootstrap/4.5.2/css/bootstrap.min.css
picamip/static/bootstrap/4.5.2/css/bootstrap.min.css.map
picamip/static/bootstrap/4.5.2/js/bootstrap.min.js
picamip/static/bootstrap/4.5.2/js/bootstrap.min.js.map
picamip/static/jquery/jquery-3.5.1.min.js
picamip/static/popper/1.16.1/popper.min.js
picamip/static/popper/1.16.1/popper.min.js.map
picamip/template/index.html
picamip/template/layout.jinja
picamip/template/macros.jinja
picamip/template/shutdown.html
picamip-1.2.0b0.data/scripts/picamip
picamip-1.2.0b0.dist-info/LICENSE.md
picamip-1.2.0b0.dist-info/METADATA
picamip-1.2.0b0.dist-info/WHEEL
picamip-1.2.0b0.dist-info/top_level.txt
picamip-1.2.0b0.dist-info/RECORD
