Metadata-Version: 2.1
Name: picamip
Version: 1.2.0b0
Summary: Simple Raspberry Pi camera http server interface
Home-page: https://github.com/luxedo/picamip
Maintainer: Luiz Eduardo Amaral
Maintainer-email: luizamaral306@gmail.com
License: BSD 3-clause "New" or "Revised License"
Keywords: raspberrypi,camera,http
Platform: UNKNOWN
Classifier: Development Status :: 4 - Beta
Classifier: Intended Audience :: Developers
Classifier: License :: OSI Approved :: BSD License
Classifier: Operating System :: POSIX :: Linux
Classifier: Programming Language :: Python :: 3.7
Classifier: Topic :: Multimedia :: Graphics :: Capture :: Digital Camera
Classifier: Topic :: Internet :: WWW/HTTP :: HTTP Servers
Requires-Python: >=3.7
Requires-Dist: picamera
Requires-Dist: flask
Provides-Extra: test
Requires-Dist: pytest ; extra == 'test'
Requires-Dist: coverage ; extra == 'test'
Requires-Dist: mypy ; extra == 'test'
Requires-Dist: pre-commit ; extra == 'test'
